[{"__type__":"cc.SpriteFrame","content":{"name":"皮肤试用@2x","texture":"1fab354d4","rect":[213,473,219,46],"offset":[0,0],"originalSize":[219,46],"rotated":1,"capInsets":[0,0,0,0]}},{"__type__":"cc.SpriteFrame","content":{"name":"武器试用@2x","texture":"1fab354d4","rect":[317,473,219,46],"offset":[0,0],"originalSize":[219,46],"rotated":1,"capInsets":[0,0,0,0]}},{"__type__":"cc.SpriteFrame","content":{"name":"星级@2x","texture":"15daeafc0","rect":[129,728,30,29],"offset":[0,0],"originalSize":[30,29],"capInsets":[0,0,0,0]}},{"__type__":"cc.SpriteFrame","content":{"name":"分享试用@2x","texture":"1979e4513","rect":[815,705,206,90],"offset":[0,0],"originalSize":[206,90],"capInsets":[0,0,0,0]}},{"__type__":"cc.SpriteFrame","content":{"name":"平台@2x","texture":"1fab354d4","rect":[756,3,264,48],"offset":[0,0],"originalSize":[264,48],"capInsets":[0,0,0,0]}},{"__type__":"cc.SpriteFrame","content":{"name":"default_sprite_splash","texture":"02delMVqdBD70a/HSD99FK","rect":[0,0,2,2],"offset":[0,0],"originalSize":[2,2],"capInsets":[0,0,0,0]}},{"__type__":"cc.SpriteFrame","content":{"name":"视频试用@2x","texture":"1979e4513","rect":[815,801,206,90],"offset":[0,0],"originalSize":[206,90],"capInsets":[0,0,0,0]}},[{"__type__":"cc.Prefab","_name":"tryPnl","data":{"__id__":1}},{"__type__":"cc.Node","_name":"tryPnl","_children":[{"__id__":2},{"__id__":3}],"_level":1,"_components":[{"__type__":"6344eS8jSRPGriAhjCIBB4j","node":{"__id__":1},"text":"try","viewname":"试用","btnname":"试用","layout":{"__id__":6},"imageList":[{"__uuid__":"03mJWZjldEiap0h2OxvKzY"},{"__uuid__":"26T9F3Qy1MVrdPyjHRgtKK"}],"titleSprite":{"__id__":5},"item":{"__id__":23}}],"_prefab":{"__type__":"cc.PrefabInfo","root":{"__id__":1},"asset":{"__uuid__":"f8va3jLDZLKqLow6t6wAxl"},"fileId":"24ybReQCNKao9wScfXHYf/"}},{"__type__":"cc.Node","_name":"shadow","_parent":{"__id__":1},"_level":2,"_components":[{"__type__":"cc.Sprite","node":{"__id__":2},"_materials":[{"__uuid__":"ecpdLyjvZBwrvm+cedCcQy"}],"_spriteFrame":{"__uuid__":"a2MjXRFdtLlYQ5ouAFv/+R"},"_sizeMode":0},{"__type__":"cc.BlockInputEvents","node":{"__id__":2}}],"_prefab":{"__type__":"cc.PrefabInfo","root":{"__id__":1},"asset":{"__uuid__":"f8va3jLDZLKqLow6t6wAxl"},"fileId":"c7hMRkWjxOKI7EMW+FuVx9"},"_opacity":220,"_color":{"__type__":"cc.Color"},"_contentSize":{"__type__":"cc.Size","width":1600,"height":1200}},{"__type__":"cc.Node","_name":"root","_parent":{"__id__":1},"_children":[{"__id__":4},{"__id__":6},{"__id__":24}],"_level":2,"_components":[{"__type__":"4b6faG4fVBLTZF8KDp18Xg+","node":{"__id__":3},"vec":{"__type__":"cc.Vec2","x":-800},"life":0,"speed":1600}],"_prefab":{"__type__":"cc.PrefabInfo","root":{"__id__":1},"asset":{"__uuid__":"f8va3jLDZLKqLow6t6wAxl"},"fileId":"424rwS5fhN+6ACSB8MT/iP"}},{"__type__":"cc.Node","_name":"title","_parent":{"__id__":3},"_level":3,"_components":[{"__id__":5}],"_prefab":{"__type__":"cc.PrefabInfo","root":{"__id__":1},"asset":{"__uuid__":"f8va3jLDZLKqLow6t6wAxl"},"fileId":"2b7rmdKKVPvZHMe59DDwkr"},"_contentSize":{"__type__":"cc.Size","width":219,"height":46},"_position":{"__type__":"cc.Vec3","y":290}},{"__type__":"cc.Sprite","node":{"__id__":4},"_materials":[{"__uuid__":"ecpdLyjvZBwrvm+cedCcQy"}],"_spriteFrame":{"__uuid__":"03mJWZjldEiap0h2OxvKzY"}},{"__type__":"cc.Node","_name":"layout","_parent":{"__id__":3},"_children":[{"__id__":7}],"_level":3,"_prefab":{"__type__":"cc.PrefabInfo","root":{"__id__":1},"asset":{"__uuid__":"f8va3jLDZLKqLow6t6wAxl"},"fileId":"e589AVAXlHLphIlbLGnZ9v"},"_contentSize":{"__type__":"cc.Size","width":280,"height":200}},{"__type__":"cc.Node","_name":"item","_parent":{"__id__":6},"_children":[{"__id__":8},{"__id__":9},{"__id__":17},{"__id__":19},{"__id__":21}],"_active":false,"_level":4,"_components":[{"__id__":23},{"__type__":"4b6faG4fVBLTZF8KDp18Xg+","node":{"__id__":7},"vec":{"__type__":"cc.Vec2","x":-800},"life":0,"speed":1600}],"_prefab":{"__type__":"cc.PrefabInfo","root":{"__id__":1},"asset":{"__uuid__":"f8va3jLDZLKqLow6t6wAxl"},"fileId":"b0/15Ajl9MuYsAS+pEdHaL"},"_contentSize":{"__type__":"cc.Size","width":280}},{"__type__":"cc.Node","_name":"skin","_parent":{"__id__":7},"_level":5,"_components":[{"__type__":"cc.Sprite","node":{"__id__":8},"_materials":[{"__uuid__":"ecpdLyjvZBwrvm+cedCcQy"}],"_spriteFrame":{"__uuid__":"7902SkDHlKZ5u1kHcgaqs1"}}],"_prefab":{"__type__":"cc.PrefabInfo","root":{"__id__":1},"asset":{"__uuid__":"f8va3jLDZLKqLow6t6wAxl"},"fileId":"5aOiqjislNQIGWzystNf96"},"_contentSize":{"__type__":"cc.Size","width":264,"height":48},"_position":{"__type__":"cc.Vec3","y":10}},{"__type__":"cc.Node","_name":"person","_parent":{"__id__":7},"_children":[{"__id__":10},{"__id__":12},{"__id__":14}],"_active":false,"_level":5,"_components":[{"__id__":16}],"_prefab":{"__type__":"cc.PrefabInfo","root":{"__id__":1},"asset":{"__uuid__":"f8va3jLDZLKqLow6t6wAxl"},"fileId":"b13B/QMClIP4usl1LaYi/z"},"_position":{"__type__":"cc.Vec3","y":15}},{"__type__":"cc.Node","_name":"skeleton","_parent":{"__id__":9},"_level":6,"_components":[{"__id__":11}],"_prefab":{"__type__":"cc.PrefabInfo","root":{"__id__":1},"asset":{"__uuid__":"f8va3jLDZLKqLow6t6wAxl"},"fileId":"21/CtJydREHZzsrIv0VxGj"},"_contentSize":{"__type__":"cc.Size","width":175.67,"height":197.67},"_scale":{"__type__":"cc.Vec3","x":-1,"y":1,"z":-1}},{"__type__":"sp.Skeleton","node":{"__id__":10},"_materials":[{"__uuid__":"7a/QZLET9IDreTiBfRn2PD"}],"_preCacheMode":0,"_animationName":"animation3"},{"__type__":"cc.Node","_name":"sprite","_parent":{"__id__":9},"_active":false,"_level":6,"_components":[{"__id__":13}],"_prefab":{"__type__":"cc.PrefabInfo","root":{"__id__":1},"asset":{"__uuid__":"f8va3jLDZLKqLow6t6wAxl"},"fileId":"93N+DE6FBOaZ17VYUaeECx"},"_contentSize":{"__type__":"cc.Size","width":200,"height":200},"_position":{"__type__":"cc.Vec3","y":-15},"_scale":{"__type__":"cc.Vec3","x":-1,"y":1,"z":-1},"_eulerAngles":{"__type__":"cc.Vec3","z":-32}},{"__type__":"cc.Sprite","node":{"__id__":12},"_materials":[{"__uuid__":"ecpdLyjvZBwrvm+cedCcQy"}],"_sizeMode":0},{"__type__":"cc.Node","_name":"startGroup","_parent":{"__id__":9},"_children":[{"__id__":15}],"_level":6,"_components":[{"__type__":"cc.Layout","node":{"__id__":14},"_layoutSize":{"__type__":"cc.Size","width":30},"_resize":1,"_N$layoutType":1}],"_prefab":{"__type__":"cc.PrefabInfo","root":{"__id__":1},"asset":{"__uuid__":"f8va3jLDZLKqLow6t6wAxl"},"fileId":"4fT37UDhdEEoErvjAFd6dN"},"_contentSize":{"__type__":"cc.Size","width":30},"_scale":{"__type__":"cc.Vec3","x":-1,"y":1,"z":-1}},{"__type__":"cc.Node","_name":"star","_parent":{"__id__":14},"_level":4,"_components":[{"__type__":"cc.Sprite","node":{"__id__":15},"_materials":[{"__uuid__":"ecpdLyjvZBwrvm+cedCcQy"}],"_spriteFrame":{"__uuid__":"4clElWnl9BfKYKcNb2A8vv"}}],"_prefab":{"__type__":"cc.PrefabInfo","root":{"__id__":1},"asset":{"__uuid__":"f8va3jLDZLKqLow6t6wAxl"},"fileId":"c9VjEHX7hOZJ9lI+zIMeeL"},"_contentSize":{"__type__":"cc.Size","width":30,"height":29},"_position":{"__type__":"cc.Vec3","x":15}},{"__type__":"99ca1xWMsNL7497dQEEdXB9","node":{"__id__":9},"skeleton":{"__id__":11},"sprite":{"__id__":13}},{"__type__":"cc.Node","_name":"sprite","_parent":{"__id__":7},"_active":false,"_level":5,"_components":[{"__id__":18}],"_prefab":{"__type__":"cc.PrefabInfo","root":{"__id__":1},"asset":{"__uuid__":"f8va3jLDZLKqLow6t6wAxl"},"fileId":"60ckNQd21O5YRNBMrJKQd4"},"_anchorPoint":{"__type__":"cc.Vec2","x":0.5},"_position":{"__type__":"cc.Vec3","y":15}},{"__type__":"cc.Sprite","node":{"__id__":17},"_materials":[{"__uuid__":"ecpdLyjvZBwrvm+cedCcQy"}],"_sizeMode":2},{"__type__":"cc.Node","_name":"videoBtn","_parent":{"__id__":7},"_active":false,"_level":4,"_components":[{"__type__":"cc.Sprite","node":{"__id__":19},"_materials":[{"__uuid__":"ecpdLyjvZBwrvm+cedCcQy"}],"_spriteFrame":{"__uuid__":"dfUpgqg29FpJioZJtcq1gT"}},{"__id__":20}],"_prefab":{"__type__":"cc.PrefabInfo","root":{"__id__":1},"asset":{"__uuid__":"f8va3jLDZLKqLow6t6wAxl"},"fileId":"8b+MhHaQdE+bWLv2IcQdua"},"_contentSize":{"__type__":"cc.Size","width":206,"height":90},"_position":{"__type__":"cc.Vec3","y":-45}},{"__type__":"cc.Button","node":{"__id__":19},"zoomScale":1.1,"clickEvents":[{"__type__":"cc.ClickEvent","target":{"__id__":1},"_componentId":"6344eS8jSRPGriAhjCIBB4j","handler":"onClickVideo"}],"_N$transition":3,"transition":3},{"__type__":"cc.Node","_name":"shareBtn","_parent":{"__id__":7},"_level":4,"_components":[{"__type__":"cc.Sprite","node":{"__id__":21},"_materials":[{"__uuid__":"ecpdLyjvZBwrvm+cedCcQy"}],"_spriteFrame":{"__uuid__":"64Bevdc4lFt4NuBTY0KvSr"}},{"__id__":22}],"_prefab":{"__type__":"cc.PrefabInfo","root":{"__id__":1},"asset":{"__uuid__":"f8va3jLDZLKqLow6t6wAxl"},"fileId":"3dVtlBwH1LZqHGVHTghg/+"},"_contentSize":{"__type__":"cc.Size","width":206,"height":90},"_position":{"__type__":"cc.Vec3","y":-45}},{"__type__":"cc.Button","node":{"__id__":21},"zoomScale":1.1,"clickEvents":[{"__type__":"cc.ClickEvent","target":{"__id__":1},"_componentId":"6344eS8jSRPGriAhjCIBB4j","handler":"onClickShare"}],"_N$transition":3,"transition":3},{"__type__":"f977d3SjEVFCoLQaqpZcmDZ","node":{"__id__":7},"videoBtn":{"__id__":20},"shareBtn":{"__id__":22},"personView":{"__id__":16},"sprite":{"__id__":18},"star":{"__id__":15}},{"__type__":"cc.Node","_name":"backBtn","_parent":{"__id__":3},"_level":3,"_components":[{"__type__":"cc.Label","node":{"__id__":24},"_materials":[{"__uuid__":"ecpdLyjvZBwrvm+cedCcQy"}],"_useOriginalSize":false,"_string":"进入游戏","_N$string":"进入游戏","_fontSize":25,"_N$horizontalAlign":1,"_N$verticalAlign":1},{"__type__":"cc.Button","node":{"__id__":24},"clickEvents":[{"__type__":"cc.ClickEvent","target":{"__id__":1},"_componentId":"6344eS8jSRPGriAhjCIBB4j","handler":"onClickBack"}],"_N$transition":1,"transition":1}],"_prefab":{"__type__":"cc.PrefabInfo","root":{"__id__":1},"asset":{"__uuid__":"f8va3jLDZLKqLow6t6wAxl"},"fileId":"7eABw3lXxJTajZNVqI/75U"},"_contentSize":{"__type__":"cc.Size","width":100,"height":50.4},"_position":{"__type__":"cc.Vec3","y":-120}}]]